sorm/__init__.py
sorm/engine.py
sorm/errors.py
sorm/objects.py
sorm/orm.py
sorm/types.py
sorm/utils.py
sorm-0.0.1.dist-info/METADATA
sorm-0.0.1.dist-info/RECORD
sorm-0.0.1.dist-info/WHEEL
sorm-0.0.1.dist-info/top_level.txt
