Metadata-Version: 2.1
Name: sorm
Version: 0.0.1
Summary: Simple SQLite3 ORM
Home-page: https://github.com/max-kim/sorm
Author: Max Kim
Author-email: kim.b2f@gmail.com
License: MIT
Platform: UNKNOWN
Classifier: Programming Language :: Python :: 3
Classifier: License :: OSI Approved :: MIT License
Classifier: Operating System :: OS Independent
